sovai/.DS_Store
sovai/__init__.py
sovai/api_config.py
sovai/assets/dropdown.css
sovai/basic_auth.py
sovai/computations/__init__.py
sovai/computations/functions.py
sovai/errors/__init__.py
sovai/errors/sovai_errors.py
sovai/extensions/__init__.py
sovai/extensions/anomalies.py
sovai/extensions/ask_df_llm.py
sovai/extensions/change_point_generator copy.py
sovai/extensions/change_point_generator.py
sovai/extensions/chart_explainer.py
sovai/extensions/clustering.py
sovai/extensions/core_kshape.py
sovai/extensions/cum_sum_torch.py
sovai/extensions/cusum.py
sovai/extensions/dimensionality_reduction.py
sovai/extensions/feature_extraction.py
sovai/extensions/feature_importance.py
sovai/extensions/feature_neutralizer.py
sovai/extensions/filter_df.py
sovai/extensions/fractional_differencing.py
sovai/extensions/nowcasting.py
sovai/extensions/overall_explainers.py
sovai/extensions/pairwise.py
sovai/extensions/pandas_extensions.py
sovai/extensions/parallel_functions.py
sovai/extensions/pfa_feature_selector.py
sovai/extensions/regime_change.py
sovai/extensions/regime_change_pca.py
sovai/extensions/shapley_global_importance.py
sovai/extensions/shapley_importance.py
sovai/extensions/signal_evaluation copy.py
sovai/extensions/signal_evaluation.py
sovai/extensions/signal_evaluation_old.py
sovai/extensions/table_explainer.py
sovai/extensions/technical_indicators.py
sovai/extensions/time_decomposition.py
sovai/extensions/weight_optimization.py
sovai/get_compute.py
sovai/get_data copy 2.py
sovai/get_data copy.py
sovai/get_data.py
sovai/get_plots.py
sovai/get_reports.py
sovai/get_tools.py
sovai/plots/__init__.py
sovai/plots/accounting/__init__.py
sovai/plots/accounting/accounting_plots.py
sovai/plots/allocation/__init__.py
sovai/plots/allocation/allocation_plots.py
sovai/plots/bankruptcy/__init__.py
sovai/plots/bankruptcy/bankruptcy_plots.py
sovai/plots/breakout/__init__.py
sovai/plots/breakout/breakout_plots.py
sovai/plots/corp_risk/__init__.py
sovai/plots/corp_risk/corp_risk_plots.py
sovai-0.2.78.dist-info/METADATA
sovai-0.2.78.dist-info/WHEEL
sovai-0.2.78.dist-info/licenses/LICENSE
sovai-0.2.78.dist-info/RECORD
