Metadata-Version: 2.4
Name: sovai
Version: 0.2.78
Summary: python for asset management
License: Proprietary License
License-File: LICENSE
Author: Derek Snow
Author-email: d.snow@outlook.com
Requires-Python: >=3.10
Classifier: License :: Other/Proprietary License
Classifier: Programming Language :: Python :: 3
Classifier: Programming Language :: Python :: 3.12
Classifier: Programming Language :: Python :: 3.13
Classifier: Programming Language :: Python :: 3.14
Provides-Extra: full
Requires-Dist: aiobotocore (==2.21.1)
Requires-Dist: boto3 (==1.37.1)
Requires-Dist: botocore (==1.37.1)
Requires-Dist: brotli (>=1.1.0,<2.0.0)
Requires-Dist: dash ; extra == "full"
Requires-Dist: dash-bootstrap-components ; extra == "full"
Requires-Dist: edgar-tool (>=1.3.3)
Requires-Dist: fastapi-cache (>=0.1.0)
Requires-Dist: fastapi-cache2[redis] (>=0.2.1)
Requires-Dist: fsspec (==2024.10.0)
Requires-Dist: gcsfs (==2024.10.0)
Requires-Dist: great-tables ; extra == "full"
Requires-Dist: ipywidgets ; extra == "full"
Requires-Dist: joblib (>=1.0)
Requires-Dist: kaleido (>=1.1.0,<2.0.0)
Requires-Dist: lightgbm ; extra == "full"
Requires-Dist: matplotlib ; extra == "full"
Requires-Dist: mfles ; extra == "full"
Requires-Dist: networkx (>=3.3)
Requires-Dist: numba ; extra == "full"
Requires-Dist: numpy (>=1.20)
Requires-Dist: openai ; extra == "full"
Requires-Dist: pandas (>=1.0)
Requires-Dist: pexpect ; extra == "full"
Requires-Dist: plotly ; extra == "full"
Requires-Dist: polars (>=1.2)
Requires-Dist: polars-talib ; extra == "full"
Requires-Dist: pyarrow (>=5.0)
Requires-Dist: python-dateutil (>=2.8)
Requires-Dist: python-dotenv (>=0.10)
Requires-Dist: pyvis (>=0.3.2)
Requires-Dist: rapidfuzz (>=3.9.7)
Requires-Dist: requests (>=2.20)
Requires-Dist: ruptures ; extra == "full"
Requires-Dist: s3fs (==2024.10.0)
Requires-Dist: s3transfer (==0.11.3)
Requires-Dist: scikit-learn ; extra == "full"
Requires-Dist: scipy ; extra == "full"
Requires-Dist: seaborn (>=0.13.2)
Requires-Dist: shap ; extra == "full"
Requires-Dist: skfolio (>=0.9.0,<0.10.0)
Requires-Dist: skfolio ; extra == "full"
Requires-Dist: statsforecast ; extra == "full"
Requires-Dist: tensorly ; extra == "full"
Requires-Dist: tqdm (>=4.67.1,<5.0.0)
Requires-Dist: yachalk (>=0.1.6)
